memsuite/__init__.py
memsuite/config.py
memsuite/db.py
memsuite/models.py
memsuite/store.py
memsuite-0.1.2.dist-info/licenses/LICENSE
memsuite-0.1.2.dist-info/METADATA
memsuite-0.1.2.dist-info/WHEEL
memsuite-0.1.2.dist-info/top_level.txt
memsuite-0.1.2.dist-info/RECORD
