Metadata-Version: 2.4
Name: memsuite
Version: 0.1.2
Summary: A lightweight, PostgreSQL-backed memory management system for AI agents and chatbots
Author-email: Sai Eswara Murali <saimurali2005@gmail.com>
Maintainer-email: Sai Eswara Murali <saimurali2005@gmail.com>
License: MIT
Project-URL: Homepage, https://github.com/saieswaramurali/memsuite
Project-URL: Repository, https://github.com/saieswaramurali/memsuite.git
Project-URL: Bug Tracker, https://github.com/saieswaramurali/memsuite/issues
Keywords: ai,memory,agents,chatbots,postgresql,llm
Classifier: Development Status :: 3 - Alpha
Classifier: Intended Audience :: Developers
Classifier: License :: OSI Approved :: MIT License
Classifier: Programming Language :: Python :: 3
Classifier: Programming Language :: Python :: 3.10
Classifier: Programming Language :: Python :: 3.11
Classifier: Programming Language :: Python :: 3.12
Classifier: Topic :: Software Development :: Libraries :: Python Modules
Classifier: Topic :: Scientific/Engineering :: Artificial Intelligence
Requires-Python: >=3.10
License-File: LICENSE
Requires-Dist: fastapi>=0.128.0
Requires-Dist: psycopg2-binary>=2.9.11
Requires-Dist: pydantic>=2.12.5
Requires-Dist: python-dotenv>=1.2.1
Requires-Dist: sqlalchemy>=2.0.46
Dynamic: license-file
